{
  "id": "event-sheet-view",
  "name_en": "The Event Sheet View",
  "name_zh": "",
  "description_en": "The Event Sheet View is where events can be added, viewed and edited in an event sheet using the event system - Construct's alternative to traditional programming. The event system has a lot of features, so the event system has its own section of the manual . This section will simply cover the basics of using the Event Sheet View. The Event Sheet View Diagram of an event The following image illustrates the key parts of an event. Events are made up of three major sections: The event block , which contains the conditions. Notice the margin to the left of the condition which allows you to select the entire event. The conditions , which are each listed inside the event block. The actions , which are listed to the right of the event block. Conditions and actions can be selected by clicking on t",
  "url": "/en/make-games/manuals/construct-3/interface/event-sheet-view",
  "sections": [
    "Diagram of an event",
    "Creating events",
    "Modifying events",
    "Scrolling and scale",
    "Finding in events"
  ]
}