{
  "id": "glowhorizontal",
  "name_zh": "水平发光",
  "name_en": "Glow horizontal",
  "description_zh": "水平采样9次的高斯发光效果。",
  "description_en": "A horizontal 9-sample gaussian glow effect.",
  "category": "color",
  "author": "Scirra",
  "supportedRenderers": [
    "webgl",
    "webgpu"
  ],
  "blendsBackground": false,
  "preservesOpaqueness": false,
  "animated": false,
  "parameters": [
    {
      "id": "intensity",
      "type": "percent",
      "name_zh": "intensity",
      "name_en": "intensity",
      "initialValue": 1,
      "interpolatable": true
    }
  ]
}