{
  "version": "1.0",
  "effects": {
    "alphaclamp": {
      "name_zh": "透明度截断",
      "name_en": "Alpha cutoff",
      "category": "color",
      "parameters": 3
    },
    "alphaclamp2": {
      "name_zh": "透明度约束",
      "name_en": "Alpha clamp",
      "category": "color",
      "parameters": 3
    },
    "alpharamp": {
      "name_zh": "透明度过渡",
      "name_en": "Alpha ramp",
      "category": "color",
      "parameters": 3
    },
    "blacknwhite": {
      "name_zh": "黑白",
      "name_en": "Black & white",
      "category": "color",
      "parameters": 1
    },
    "blacknwhitemask": {
      "name_zh": "黑白蒙版",
      "name_en": "Black & white mask",
      "category": "mask",
      "parameters": 1
    },
    "blurhorizontal": {
      "name_zh": "水平模糊",
      "name_en": "Blur horizontal",
      "category": "color",
      "parameters": 1
    },
    "blurvertical": {
      "name_zh": "垂直模糊",
      "name_en": "Blur vertical",
      "category": "color",
      "parameters": 1
    },
    "brightness": {
      "name_zh": "亮度",
      "name_en": "Brightness",
      "category": "color",
      "parameters": 1
    },
    "bulge": {
      "name_zh": "膨胀",
      "name_en": "Bulge",
      "category": "distortion",
      "parameters": 2
    },
    "bumpmapping": {
      "name_zh": "凹凸映射",
      "name_en": "Bumpmapping",
      "category": "normal-mapping",
      "parameters": 4
    },
    "burn": {
      "name_zh": "加深",
      "name_en": "Burn",
      "category": "blend",
      "parameters": 0
    },
    "cga": {
      "name_zh": "CGA",
      "name_en": "CGA",
      "category": "color",
      "parameters": 0
    },
    "colorblend": {
      "name_zh": "颜色",
      "name_en": "Color",
      "category": "blend",
      "parameters": 0
    },
    "colorhalftone": {
      "name_zh": "彩色半调",
      "name_en": "Color halftone",
      "category": "color",
      "parameters": 2
    },
    "contrast": {
      "name_zh": "对比度",
      "name_en": "Contrast",
      "category": "color",
      "parameters": 1
    },
    "crosshatch": {
      "name_zh": "阴影线",
      "name_en": "Crosshatch",
      "category": "color",
      "parameters": 2
    },
    "crystalball": {
      "name_zh": "水晶球",
      "name_en": "Crystal ball",
      "category": "distortion",
      "parameters": 2
    },
    "darken": {
      "name_zh": "变暗",
      "name_en": "Darken",
      "category": "blend",
      "parameters": 0
    },
    "depthstripe": {
      "name_zh": "深度条纹",
      "name_en": "Depth stripe",
      "category": "3d",
      "parameters": 6
    },
    "difference": {
      "name_zh": "差值",
      "name_en": "Difference",
      "category": "blend",
      "parameters": 0
    },
    "divide": {
      "name_zh": "划分",
      "name_en": "Divide",
      "category": "blend",
      "parameters": 0
    },
    "dodge": {
      "name_zh": "减淡",
      "name_en": "Dodge",
      "category": "blend",
      "parameters": 0
    },
    "dotscreen": {
      "name_zh": "半调",
      "name_en": "Dot screen",
      "category": "color",
      "parameters": 2
    },
    "emboss": {
      "name_zh": "浮雕",
      "name_en": "Emboss",
      "category": "color",
      "parameters": 1
    },
    "exclusion": {
      "name_zh": "排除",
      "name_en": "Exclusion",
      "category": "blend",
      "parameters": 0
    },
    "exposure": {
      "name_zh": "曝光",
      "name_en": "Exposure",
      "category": "color",
      "parameters": 1
    },
    "fogexponential": {
      "name_zh": "雾场",
      "name_en": "Fog (exponential)",
      "category": "3d",
      "parameters": 3
    },
    "gamma": {
      "name_zh": "伽马",
      "name_en": "Gamma",
      "category": "color",
      "parameters": 1
    },
    "glass": {
      "name_zh": "玻璃",
      "name_en": "Glass",
      "category": "distortion",
      "parameters": 1
    },
    "glowhorizontal": {
      "name_zh": "水平发光",
      "name_en": "Glow horizontal",
      "category": "color",
      "parameters": 1
    },
    "glowvertical": {
      "name_zh": "垂直发光",
      "name_en": "Glow vertical",
      "category": "color",
      "parameters": 1
    },
    "grayscale": {
      "name_zh": "灰度",
      "name_en": "Grayscale",
      "category": "color",
      "parameters": 1
    },
    "grayscalemask": {
      "name_zh": "灰度蒙版",
      "name_en": "Grayscale mask",
      "category": "mask",
      "parameters": 0
    },
    "hardlight": {
      "name_zh": "强光",
      "name_en": "Hard light",
      "category": "blend",
      "parameters": 0
    },
    "hexpixellate": {
      "name_zh": "像素化(晶体)",
      "name_en": "Hexagonal pixellate",
      "category": "color",
      "parameters": 1
    },
    "hexpixellatemask": {
      "name_zh": "晶体像素化蒙版",
      "name_en": "Hexagonal pixellate mask",
      "category": "mask",
      "parameters": 1
    },
    "highlightshadow": {
      "name_zh": "高光阴影",
      "name_en": "Highlight shadow",
      "category": "color",
      "parameters": 2
    },
    "hsladjust": {
      "name_zh": "HSL调整",
      "name_en": "Adjust HSL",
      "category": "color",
      "parameters": 3
    },
    "hsladjustmask": {
      "name_zh": "HSL调整蒙版",
      "name_en": "Adjust HSL mask",
      "category": "mask",
      "parameters": 3
    },
    "hueblend": {
      "name_zh": "色相",
      "name_en": "Hue",
      "category": "blend",
      "parameters": 0
    },
    "inverse": {
      "name_zh": "反相",
      "name_en": "Inverse",
      "category": "color",
      "parameters": 1
    },
    "lens2": {
      "name_zh": "放大镜",
      "name_en": "Lens2",
      "category": "distortion",
      "parameters": 1
    },
    "lighten": {
      "name_zh": "亮度",
      "name_en": "Lighten",
      "category": "blend",
      "parameters": 0
    },
    "lumblend": {
      "name_zh": "明度",
      "name_en": "Luminosity",
      "category": "blend",
      "parameters": 0
    },
    "multiply": {
      "name_zh": "正片叠底",
      "name_en": "Multiply",
      "category": "blend",
      "parameters": 0
    },
    "noise": {
      "name_zh": "噪点",
      "name_en": "Noise",
      "category": "color",
      "parameters": 2
    },
    "noisemask": {
      "name_zh": "噪点蒙版",
      "name_en": "Noise mask",
      "category": "mask",
      "parameters": 2
    },
    "oilpainting": {
      "name_zh": "油画",
      "name_en": "Oil painting",
      "category": "color",
      "parameters": 0
    },
    "overlay": {
      "name_zh": "叠加",
      "name_en": "Overlay",
      "category": "blend",
      "parameters": 0
    },
    "pixellate": {
      "name_zh": "像素化",
      "name_en": "Pixellate",
      "category": "color",
      "parameters": 1
    },
    "pixellatemask": {
      "name_zh": "像素化蒙版",
      "name_en": "Pixellate mask",
      "category": "mask",
      "parameters": 1
    },
    "polarinvert": {
      "name_zh": "极反转",
      "name_en": "Polar invert",
      "category": "distortion",
      "parameters": 1
    },
    "polkadot": {
      "name_zh": "圆点",
      "name_en": "Polka dot",
      "category": "color",
      "parameters": 2
    },
    "posterize": {
      "name_zh": "色调分离",
      "name_en": "Posterize",
      "category": "color",
      "parameters": 1
    },
    "posterizemask": {
      "name_zh": "色调分离蒙版",
      "name_en": "Posterize mask",
      "category": "mask",
      "parameters": 1
    },
    "pulse": {
      "name_zh": "脉冲",
      "name_en": "Pulse",
      "category": "distortion",
      "parameters": 6
    },
    "radialblur": {
      "name_zh": "径向模糊",
      "name_en": "Radial blur",
      "category": "color",
      "parameters": 2
    },
    "radialpixellate": {
      "name_zh": "像素化(径向)",
      "name_en": "Radial pixellate",
      "category": "color",
      "parameters": 1
    },
    "radialpixellatemask": {
      "name_zh": "径向像素化蒙版",
      "name_en": "Radial pixellate mask",
      "category": "mask",
      "parameters": 1
    },
    "randomizetiling": {
      "name_zh": "平铺扰动",
      "name_en": "Randomize tiling",
      "category": "tiling",
      "parameters": 7
    },
    "replacecolor": {
      "name_zh": "替换颜色",
      "name_en": "Replace color",
      "category": "color",
      "parameters": 3
    },
    "replacesolidcolor": {
      "name_zh": "替换纯色",
      "name_en": "Replace solid color",
      "category": "color",
      "parameters": 3
    },
    "satblend": {
      "name_zh": "饱和度",
      "name_en": "Saturation",
      "category": "blend",
      "parameters": 0
    },
    "scanlines": {
      "name_zh": "扫描线",
      "name_en": "Scan lines",
      "category": "color",
      "parameters": 1
    },
    "screen": {
      "name_zh": "滤色",
      "name_en": "Screen",
      "category": "blend",
      "parameters": 0
    },
    "sepia": {
      "name_zh": "怀旧",
      "name_en": "Sepia",
      "category": "color",
      "parameters": 1
    },
    "sepiamask": {
      "name_zh": "怀旧蒙版",
      "name_en": "Sepia mask",
      "category": "mask",
      "parameters": 0
    },
    "setcolor": {
      "name_zh": "颜色覆盖",
      "name_en": "Set color",
      "category": "color",
      "parameters": 1
    },
    "sharpen": {
      "name_zh": "锐化",
      "name_en": "Sharpen",
      "category": "color",
      "parameters": 1
    },
    "sketch": {
      "name_zh": "素描",
      "name_en": "Sketch",
      "category": "color",
      "parameters": 0
    },
    "softlight": {
      "name_zh": "柔光",
      "name_en": "Soft light",
      "category": "blend",
      "parameters": 0
    },
    "sphere": {
      "name_zh": "球面",
      "name_en": "Sphere",
      "category": "distortion",
      "parameters": 3
    },
    "stretch": {
      "name_zh": "拉伸",
      "name_en": "Stretch",
      "category": "distortion",
      "parameters": 0
    },
    "subtract": {
      "name_zh": "减去",
      "name_en": "Subtract",
      "category": "blend",
      "parameters": 0
    },
    "swirl": {
      "name_zh": "漩涡",
      "name_en": "Swirl",
      "category": "distortion",
      "parameters": 2
    },
    "tint": {
      "name_zh": "颜色叠加",
      "name_en": "Tint",
      "category": "color",
      "parameters": 1
    },
    "tintmask": {
      "name_zh": "颜色叠加蒙版",
      "name_en": "Tint mask",
      "category": "mask",
      "parameters": 1
    },
    "toon": {
      "name_zh": "卡通",
      "name_en": "Toon",
      "category": "color",
      "parameters": 2
    },
    "vibrance": {
      "name_zh": "自然饱和度",
      "name_en": "Vibrance",
      "category": "color",
      "parameters": 1
    },
    "vignette": {
      "name_zh": "暗角",
      "name_en": "Vignette",
      "category": "color",
      "parameters": 2
    },
    "warp": {
      "name_zh": "变形",
      "name_en": "Warp",
      "category": "distortion",
      "parameters": 6
    },
    "warpobject": {
      "name_zh": "对象扭曲",
      "name_en": "Warp object",
      "category": "distortion",
      "parameters": 6
    },
    "warpobjectmask": {
      "name_zh": "扭曲对象蒙版",
      "name_en": "Warp object mask",
      "category": "mask",
      "parameters": 6
    },
    "warplayout": {
      "name_zh": "场景扭曲",
      "name_en": "Warp layout",
      "category": "distortion",
      "parameters": 6
    },
    "warpmask": {
      "name_zh": "扭曲蒙版",
      "name_en": "Warp mask",
      "category": "mask",
      "parameters": 6
    },
    "warpradial": {
      "name_zh": "径向扭曲",
      "name_en": "Warp radial",
      "category": "distortion",
      "parameters": 3
    },
    "warpripple": {
      "name_zh": "波纹扭曲",
      "name_en": "Warp ripple",
      "category": "distortion",
      "parameters": 3
    },
    "water": {
      "name_zh": "水面",
      "name_en": "Water",
      "category": "distortion",
      "parameters": 9
    },
    "waterbg": {
      "name_zh": "水面背景",
      "name_en": "Water background",
      "category": "distortion",
      "parameters": 9
    }
  },
  "stats": {
    "count": 89
  }
}