{
  "id": "vignette",
  "name_zh": "暗角",
  "name_en": "Vignette",
  "description_zh": "淡出屏幕周围的边缘。",
  "description_en": "Fade out the edges around the screen.",
  "category": "color",
  "author": "Brad Larson",
  "supportedRenderers": [
    "webgl",
    "webgpu"
  ],
  "blendsBackground": false,
  "preservesOpaqueness": true,
  "animated": false,
  "parameters": [
    {
      "id": "start-radius",
      "type": "percent",
      "name_zh": "start-radius",
      "name_en": "start-radius",
      "initialValue": 0.3,
      "interpolatable": true
    },
    {
      "id": "end-radius",
      "type": "percent",
      "name_zh": "end-radius",
      "name_en": "end-radius",
      "initialValue": 0.75,
      "interpolatable": true
    }
  ]
}