{
  "id": "asset-browser-bar-settings",
  "name_zh": "资源库设置",
  "name_en": "Asset Browser settings",
  "strings": {
    "import-animations-settings": {
      "zh": "导入设置",
      "en": "Animations import settings"
    },
    "use-file-name-as-frame-tag-on-many": {
      "zh": "导入多个对象类型时，使用资产名称作为动画帧属性",
      "en": "Tag new frames with asset name when importing as many object types"
    },
    "use-file-name-as-frame-tag-on-single": {
      "zh": "导入单个对象类型时，使用资产名称作为动画帧属性",
      "en": "Tag new frames with asset name when importing as single object type"
    },
    "use-file-name-as-frame-tag-sub-2": {
      "zh": "导入 .zip 压缩包时将优先使用 [a1]c3-import-settings.json[/a1] 的配置信息",
      "en": "• zip files with a [a1]c3-import-settings.json[/a1] file will prefer tag values in that file"
    },
    "use-file-name-as-frame-tag-sub-1": {
      "zh": "• 这些不适用于动画格式 (如. [b].gif[/b], [b].apng[/b])",
      "en": "• these do not apply for animated formats (e.g. [b].gif[/b] or [b].apng[/b])"
    }
  }
}